_test_helpers/__init__.py
_test_helpers/spam/__init__.py
_test_helpers/spam_with_egg/__init__.py
cfx_utils/__init__.py
cfx_utils/decorators.py
cfx_utils/exceptions.py
cfx_utils/post_import_hook.py
cfx_utils/py.typed
cfx_utils/token_unit.py
cfx_utils/types.py
cfx_utils-1.1.0.dist-info/METADATA
cfx_utils-1.1.0.dist-info/WHEEL
cfx_utils-1.1.0.dist-info/top_level.txt
cfx_utils-1.1.0.dist-info/RECORD
