Metadata-Version: 2.1
Name: cfx-utils
Version: 1.1.0
Summary: cfx-utils: Common utils for conflux python packages
Home-page: https://github.com/conflux-fans/cfx-utils
Author: Conflux-Dev
Author-email: wenda.zhang@confluxnetwork.org
License: MIT
Keywords: conflux
Classifier: Development Status :: 3 - Alpha
Classifier: Intended Audience :: Education
Classifier: Programming Language :: Python :: 2
Classifier: Programming Language :: Python :: 3
Classifier: Operating System :: MacOS :: MacOS X
Classifier: Operating System :: Microsoft :: Windows
Requires-Python: >=3.7
Requires-Dist: typing-extensions>=4.2.0
Requires-Dist: hexbytes
Requires-Dist: eth-typing>=2.0.0
Provides-Extra: dev
Requires-Dist: bumpversion<1,>=0.5.3; extra == "dev"
Requires-Dist: wheel; extra == "dev"
Requires-Dist: twine; extra == "dev"
Requires-Dist: ipython; extra == "dev"
Requires-Dist: pytest<9,>=8; extra == "dev"
Requires-Dist: cfx-address>=1.2.0; extra == "dev"
Provides-Extra: doc
Provides-Extra: lint
Provides-Extra: test
Requires-Dist: pytest<9,>=8; extra == "test"
Requires-Dist: cfx-address>=1.2.0; extra == "test"
